README.md
setup.py
ig_scraper/__init__.py
ig_scraper/__version__.py
ig_scraper/constants.py
ig_scraper/scraper.py
ig_scraper.egg-info/PKG-INFO
ig_scraper.egg-info/SOURCES.txt
ig_scraper.egg-info/dependency_links.txt
ig_scraper.egg-info/requires.txt
ig_scraper.egg-info/top_level.txt