Metadata-Version: 1.1
Name: ig-scraper
Version: 0.1.0
Summary: Instagram hashtag scraper
Home-page: https://github.com/kangfend/ig-scraper
Author: Sutrisno Efendi
Author-email: kangfend@gmail.com
License: MIT
Download-URL: https://github.com/kangfend/ig-scraper/tarball/0.1.0
Keywords: Instagram,Scraper
Platform: UNKNOWN
Classifier: Development Status :: 3 - Alpha
Classifier: Intended Audience :: Developers
Classifier: Programming Language :: Python
Classifier: License :: OSI Approved :: MIT License
Classifier: Operating System :: OS Independent
Classifier: Topic :: Internet :: WWW/HTTP
Classifier: Topic :: Software Development :: Libraries :: Python Modules
